report/__init__.py
report/main.py
report/report_maker.py
report_of_monaco_2018_racing-0.1.1.dist-info/METADATA
report_of_monaco_2018_racing-0.1.1.dist-info/WHEEL
report_of_monaco_2018_racing-0.1.1.dist-info/entry_points.txt
report_of_monaco_2018_racing-0.1.1.dist-info/RECORD
