Metadata-Version: 2.3
Name: report-of-monaco-2018-racing
Version: 0.1.1
Summary: Генератор звіту про гонку F1 Monaco 2018 з CLI інтерфейсом
Author: Daniel Kravchenko
Author-email: daniel.kravchenko@protonmail.com
Requires-Python: >=3.12
Classifier: Programming Language :: Python :: 3
Classifier: Programming Language :: Python :: 3.12
Classifier: Programming Language :: Python :: 3.13
Requires-Dist: build (>=1.2.2.post1,<2.0.0)
Requires-Dist: twine (>=6.1.0,<7.0.0)
